twigs/__init__.py
twigs/acr.py
twigs/aws.py
twigs/aws_cis.py
twigs/az_cis_metadata.py
twigs/azure.py
twigs/azure_cis.py
twigs/azure_functions.py
twigs/code_secrets.py
twigs/code_secrets_defaults.py
twigs/dast.py
twigs/dna_center.py
twigs/docker.py
twigs/docker_cis.py
twigs/ecr.py
twigs/fingerprint.py
twigs/gcloud_functions.py
twigs/gcp.py
twigs/gcp_cis.py
twigs/gcr.py
twigs/gd-ca-bundle.crt
twigs/iac.py
twigs/iac_meta.py
twigs/k8s_cis.py
twigs/kubernetes.py
twigs/linux.py
twigs/meraki.py
twigs/o365.py
twigs/oci.py
twigs/oci_cis.py
twigs/oci_utils.py
twigs/ocr.py
twigs/plugin_processor.py
twigs/plugin_registry.py
twigs/policy.py
twigs/repo.py
twigs/sast.py
twigs/sbom.py
twigs/servicenow.py
twigs/ssh-audit.py
twigs/ssl_audit.py
twigs/th_secrets.py
twigs/twigs.py
twigs/utils.py
twigs/vmware.py
twigs/website.py
twigs/windows.py
twigs/azure_cis_tool/__init__.py
twigs/azure_cis_tool/az_cis_check1.py
twigs/azure_cis_tool/az_cis_check2.py
twigs/azure_cis_tool/az_cis_check3.py
twigs/azure_cis_tool/az_cis_check4.py
twigs/azure_cis_tool/az_cis_check5.py
twigs/azure_cis_tool/az_cis_check6.py
twigs/azure_cis_tool/az_cis_check7.py
twigs/azure_cis_tool/az_cis_check8.py
twigs/azure_cis_tool/az_cis_utils.py
twigs/azure_cis_tool/azure_cis.py
twigs/dast_plugins/__init__.py
twigs/dast_plugins/arachni.py
twigs/dast_plugins/skipfish.py
twigs/dast_plugins/zap.py
twigs/gcp_cis_tool/__init__.py
twigs/gcp_cis_tool/check1.py
twigs/gcp_cis_tool/check2.py
twigs/gcp_cis_tool/check3.py
twigs/gcp_cis_tool/check4.py
twigs/gcp_cis_tool/check5.py
twigs/gcp_cis_tool/check6.py
twigs/gcp_cis_tool/check7.py
twigs/gcp_cis_tool/gcp_cis.py
twigs/gcp_cis_tool/gcp_cis_utils.py
twigs/gcp_cis_tool/recommendations.json
twigs/host_benchmark/__init__.py
twigs/host_benchmark/host_benchmark.py
twigs/host_benchmark/lynis-3.1.1.tar.gz
twigs/host_benchmark/recommendations.json
twigs/kubernetes-cis-benchmark/LICENSE
twigs/kubernetes-cis-benchmark/federation.sh
twigs/kubernetes-cis-benchmark/helper.sh
twigs-1.2.87.dist-info/AUTHORS.rst
twigs-1.2.87.dist-info/LICENSE
twigs-1.2.87.dist-info/METADATA
twigs-1.2.87.dist-info/WHEEL
twigs-1.2.87.dist-info/entry_points.txt
twigs-1.2.87.dist-info/top_level.txt
twigs-1.2.87.dist-info/RECORD
