Metadata-Version: 2.1
Name: twigs
Version: 1.2.87
Summary: ThreatWorx Information Gathering Script
Home-page: https://github.com/threatworx/twigs
Author: Paresh Borkar
Author-email: opensource@threatwatch.io
License: GNU General Public License v3
Keywords: twigs
Classifier: Development Status :: 5 - Production/Stable
Classifier: Intended Audience :: Developers
Classifier: Intended Audience :: Information Technology
Classifier: License :: OSI Approved :: GNU General Public License v3 (GPLv3)
Classifier: Natural Language :: English
Classifier: Programming Language :: Python :: 3 :: Only
Classifier: Programming Language :: Python :: 3.4
Classifier: Programming Language :: Python :: 3.5
Classifier: Programming Language :: Python :: 3.6
Classifier: Programming Language :: Python :: 3.7
License-File: LICENSE
License-File: AUTHORS.rst
Requires-Dist: boto3
Requires-Dist: cryptography ==3.3.2
Requires-Dist: ipaddress
Requires-Dist: ipaddress ==1.0.22
Requires-Dist: oci-cli ==3.43.1
Requires-Dist: paramiko ==2.6.0
Requires-Dist: pefile ==2019.4.18
Requires-Dist: psutil
Requires-Dist: pysnow
Requires-Dist: python-crontab ==2.5.1
Requires-Dist: pytz
Requires-Dist: pyvmomi ==7.0.3
Requires-Dist: pywinrm ==0.5.0
Requires-Dist: pyyaml >5.1
Requires-Dist: requests
Requires-Dist: requirements-parser
Requires-Dist: scp ==0.13.3
Requires-Dist: setuptools
Requires-Dist: toml ==0.10.2
